rayleaf/__init__.py
rayleaf/main.py
rayleaf/core/__init__.py
rayleaf/core/client_cluster.py
rayleaf/entities/__init__.py
rayleaf/entities/client.py
rayleaf/entities/constants.py
rayleaf/entities/server.py
rayleaf/models/__init__.py
rayleaf/models/model.py
rayleaf/models/model_constants.py
rayleaf/models/utils.py
rayleaf/models/celeba/__init__.py
rayleaf/models/celeba/cnn.py
rayleaf/models/femnist/__init__.py
rayleaf/models/femnist/cnn.py
rayleaf/models/reddit/__init__.py
rayleaf/models/reddit/stacked_lstm.py
rayleaf/models/sent140/__init__.py
rayleaf/models/sent140/bag_log_reg.py
rayleaf/models/sent140/get_embs.py
rayleaf/models/sent140/get_embs.sh
rayleaf/models/sent140/stacked_lstm.py
rayleaf/models/shakespeare/__init__.py
rayleaf/models/shakespeare/stacked_lstm.py
rayleaf/models/speech_commands/__init__.py
rayleaf/models/speech_commands/initialize_data.py
rayleaf/models/speech_commands/m5.py
rayleaf/models/speech_commands/utils.py
rayleaf/models/synthetic/__init__.py
rayleaf/models/synthetic/log_reg.py
rayleaf/stage/__init__.py
rayleaf/stage/eval_stage.py
rayleaf/stage/graph_stage.py
rayleaf/stage/setup_stage.py
rayleaf/stage/teardown_stage.py
rayleaf/stage/train_stage.py
rayleaf/stats/__init__.py
rayleaf/stats/graphing.py
rayleaf/tensorarray/tensorarray.py
rayleaf/tensorarray/utils.py
rayleaf/utils/__init__.py
rayleaf/utils/client_count_utils.py
rayleaf/utils/data_utils.py
rayleaf/utils/language_utils.py
rayleaf/utils/logging_utils.py
rayleaf-0.0.12.dist-info/METADATA
rayleaf-0.0.12.dist-info/WHEEL
rayleaf-0.0.12.dist-info/licenses/LICENSE.md
rayleaf-0.0.12.dist-info/RECORD
