Metadata-Version: 2.1
Name: rayleaf
Version: 0.0.12
Summary: RayLEAF: a flexible, highly-scalable benchmark for federated learning
Project-URL: Homepage, https://github.com/rizhu/rayleaf
Author-email: Richard Hu <r.hu@berkeley.edu>
License: BSD 2-Clause License
License-File: LICENSE.md
Classifier: License :: OSI Approved :: MIT License
Classifier: Operating System :: OS Independent
Classifier: Programming Language :: Python :: 3
Requires-Python: >=3.10.4
Requires-Dist: aiohttp-cors>=0.7.0
Requires-Dist: aiohttp>=3.7.4
Requires-Dist: matplotlib>=3.5.2
Requires-Dist: numpy>=1.23.0
Requires-Dist: opencensus>=0.11.0
Requires-Dist: pandas>=1.4.3
Requires-Dist: pillow>=9.2.0
Requires-Dist: prometheus-client>=0.14.1
Requires-Dist: ray[default]>=2.0.0
Requires-Dist: scipy>=1.9.1
Requires-Dist: tabulate>=0.8.10
Requires-Dist: thop>=0.1.1.post2207130030
Requires-Dist: torch>=1.12.1
Requires-Dist: torchaudio>=0.12.1
Requires-Dist: torchvision>=0.13.1
Requires-Dist: tqdm>=4.64.0
